{
  "cidade": "Lago dos Rodrigues",
  "estado": "MA",
  "slug": "lago-dos-rodrigues",
  "latitude": -4.5886,
  "longitude": -44.9309,
  "atualizado_em": "2026-06-22T13:32:43.033977+00:00",
  "previsao": [
    {
      "data": "2026-06-22",
      "min": 22.8,
      "max": 31.0,
      "condicao": "Chuvisco leve",
      "condicao_codigo": 51,
      "chuva_mm": 0.5,
      "uv": 7.4,
      "nascer_sol": "06:06",
      "por_sol": "17:57"
    },
    {
      "data": "2026-06-23",
      "min": 23.2,
      "max": 31.3,
      "condicao": "Chuvisco leve",
      "condicao_codigo": 51,
      "chuva_mm": 0.3,
      "uv": 7.4,
      "nascer_sol": "06:06",
      "por_sol": "17:57"
    },
    {
      "data": "2026-06-24",
      "min": 23.2,
      "max": 30.7,
      "condicao": "Chuvisco leve",
      "condicao_codigo": 51,
      "chuva_mm": 1.2,
      "uv": 7.4,
      "nascer_sol": "06:06",
      "por_sol": "17:58"
    },
    {
      "data": "2026-06-25",
      "min": 23.4,
      "max": 30.5,
      "condicao": "Chuvisco leve",
      "condicao_codigo": 51,
      "chuva_mm": 0.5,
      "uv": 7.4,
      "nascer_sol": "06:06",
      "por_sol": "17:58"
    },
    {
      "data": "2026-06-26",
      "min": 21.3,
      "max": 31.3,
      "condicao": "Chuvisco leve",
      "condicao_codigo": 51,
      "chuva_mm": 0.3,
      "uv": 7.4,
      "nascer_sol": "06:07",
      "por_sol": "17:58"
    },
    {
      "data": "2026-06-27",
      "min": 23.4,
      "max": 31.5,
      "condicao": "Chuvisco moderado",
      "condicao_codigo": 53,
      "chuva_mm": 4.7,
      "uv": 5.2,
      "nascer_sol": "06:07",
      "por_sol": "17:58"
    },
    {
      "data": "2026-06-28",
      "min": 23.2,
      "max": 30.9,
      "condicao": "Chuvisco moderado",
      "condicao_codigo": 53,
      "chuva_mm": 3.4,
      "uv": 7.0,
      "nascer_sol": "06:07",
      "por_sol": "17:58"
    }
  ],
  "queimadas": {
    "focos_100km": 3,
    "fonte": "NASA FIRMS / INPE",
    "atualizado_em": "2026-06-22T12:29:47.066882+00:00"
  },
  "uv": {
    "indice": 7.4,
    "categoria": "Alto",
    "fonte": "Open-Meteo",
    "pico_inicio": "10:00",
    "pico_fim": "14:00"
  },
  "qualidade_ar": {
    "indice": 31,
    "categoria": "Boa",
    "principal_poluente": "PM2.5",
    "pm25": 4.8,
    "pm10": 6.8,
    "no2": 0.2,
    "o3": 65.0,
    "fonte": "Open-Meteo / Copernicus",
    "atualizado_em": "2026-06-22T13:32:43.033977+00:00"
  },
  "sol": {
    "nascer": "06:06",
    "por": "17:57",
    "duracao_h": 11.9,
    "estacao": "Inverno",
    "fonte": "Open-Meteo"
  },
  "lua": {
    "nome": "Crescente",
    "iluminacao_pct": 99.0,
    "fase_pct": 23.4,
    "dias_proxima_cheia": 8,
    "fonte": "Cálculo astronômico"
  },
  "temperatura_atual": 28.8,
  "vento": {
    "velocidade_kmh": 8.1,
    "direcao_graus": 55,
    "direcao": "NE",
    "max_kmh": 10.3,
    "rajada_kmh": 23.8,
    "direcao_dominante": "NE",
    "fonte": "Open-Meteo"
  },
  "umidade_pct": 78,
  "pressao_hpa": 1015,
  "ponto_orvalho_c": 24.5,
  "dengue": {
    "nivel_alerta": 1,
    "nivel_label": "Atenção",
    "nivel_incidencia": 0,
    "nivel_incidencia_label": "Baixa",
    "casos_semana": 0,
    "casos_estimados": 0,
    "semana_epidemiologica": 202620,
    "fonte": "InfoDengue / Fiocruz / SVS",
    "atualizado_em": "2026-06-01T22:07:55.191770-03:00"
  },
  "chikungunya": {
    "nivel_alerta": 1,
    "nivel_label": "Atenção",
    "nivel_incidencia": 0,
    "nivel_incidencia_label": "Baixa",
    "casos_semana": 0,
    "casos_estimados": 0,
    "semana_epidemiologica": 202620,
    "fonte": "InfoDengue / Fiocruz / SVS",
    "atualizado_em": "2026-06-01T22:07:55.191770-03:00"
  },
  "_clima_em": "2026-06-22T13:32:43.033977+00:00"
}