{
  "cidade": "Raposa",
  "estado": "MA",
  "slug": "raposa",
  "latitude": -2.4376,
  "longitude": -44.0897,
  "atualizado_em": "2026-06-29T09:32:18.558522+00:00",
  "previsao": [
    {
      "data": "2026-06-29",
      "min": 25,
      "max": 30,
      "condicao": "Chuva",
      "condicao_codigo": "c",
      "chuva_mm": 0,
      "umidade": 0,
      "uv": 0.0
    },
    {
      "data": "2026-06-30",
      "min": 26,
      "max": 32,
      "condicao": "Chuvas Isoladas",
      "condicao_codigo": "ci",
      "chuva_mm": 0,
      "umidade": 0,
      "uv": 0.0
    },
    {
      "data": "2026-07-01",
      "min": 26,
      "max": 32,
      "condicao": "Parcialmente Nublado",
      "condicao_codigo": "pn",
      "chuva_mm": 0,
      "umidade": 0,
      "uv": 0.0
    },
    {
      "data": "2026-07-02",
      "min": 26,
      "max": 32,
      "condicao": "Parcialmente Nublado",
      "condicao_codigo": "pn",
      "chuva_mm": 0,
      "umidade": 0,
      "uv": 0.0
    }
  ],
  "queimadas": {
    "focos_100km": 0,
    "fonte": "NASA FIRMS / INPE",
    "atualizado_em": "2026-06-28T09:39:12.501847+00:00"
  },
  "uv": {
    "indice": 7.6,
    "categoria": "Alto",
    "fonte": "Open-Meteo",
    "pico_inicio": "10:00",
    "pico_fim": "14:00"
  },
  "qualidade_ar": {
    "indice": 24,
    "categoria": "Boa",
    "principal_poluente": "PM10",
    "pm25": 5.3,
    "pm10": 8.7,
    "no2": 0.8,
    "o3": 41.0,
    "fonte": "Open-Meteo / Copernicus",
    "atualizado_em": "2026-06-27T10:04:31.375182+00:00"
  },
  "sol": {
    "nascer": "05:59",
    "por": "17:58",
    "duracao_h": 12.0,
    "estacao": "Inverno",
    "fonte": "Open-Meteo"
  },
  "lua": {
    "nome": "Gibosa Crescente",
    "iluminacao_pct": 57.0,
    "fase_pct": 40.3,
    "dias_proxima_cheia": 3,
    "fonte": "Cálculo astronômico"
  },
  "temperatura_atual": 27.0,
  "vento": {
    "velocidade_kmh": 17.9,
    "direcao_graus": 100,
    "direcao": "E",
    "max_kmh": 22.6,
    "rajada_kmh": 47.5,
    "direcao_dominante": "ENE",
    "fonte": "Open-Meteo"
  },
  "umidade_pct": 81,
  "pressao_hpa": 1014,
  "ponto_orvalho_c": 23.4,
  "dengue": {
    "nivel_alerta": 2,
    "nivel_label": "Alerta",
    "nivel_incidencia": 2,
    "nivel_incidencia_label": "Alta",
    "casos_semana": 0,
    "casos_estimados": 25,
    "semana_epidemiologica": 202620,
    "fonte": "InfoDengue / Fiocruz / SVS",
    "atualizado_em": "2026-06-01T22:07:55.191770-03:00"
  },
  "chikungunya": {
    "nivel_alerta": 1,
    "nivel_label": "Atenção",
    "nivel_incidencia": 0,
    "nivel_incidencia_label": "Baixa",
    "casos_semana": 0,
    "casos_estimados": 0,
    "semana_epidemiologica": 202620,
    "fonte": "InfoDengue / Fiocruz / SVS",
    "atualizado_em": "2026-06-01T22:07:55.191770-03:00"
  },
  "_clima_em": "2026-06-27T10:04:31.375182+00:00"
}