{
  "cidade": "São Bernardo",
  "estado": "MA",
  "slug": "sao-bernardo",
  "latitude": -3.312,
  "longitude": -42.4061,
  "atualizado_em": "2026-06-25T08:29:27.604734+00:00",
  "previsao": [
    {
      "data": "2026-06-25",
      "min": 25,
      "max": 33,
      "condicao": "Parcialmente Nublado",
      "condicao_codigo": "pn",
      "chuva_mm": 0,
      "umidade": 0,
      "uv": 0.0
    },
    {
      "data": "2026-06-26",
      "min": 24,
      "max": 32,
      "condicao": "Parcialmente Nublado",
      "condicao_codigo": "pn",
      "chuva_mm": 0,
      "umidade": 0,
      "uv": 0.0
    },
    {
      "data": "2026-06-27",
      "min": 24,
      "max": 34,
      "condicao": "Parcialmente Nublado",
      "condicao_codigo": "pn",
      "chuva_mm": 0,
      "umidade": 0,
      "uv": 0.0
    },
    {
      "data": "2026-06-28",
      "min": 24,
      "max": 34,
      "condicao": "Parcialmente Nublado",
      "condicao_codigo": "pn",
      "chuva_mm": 0,
      "umidade": 0,
      "uv": 0.0
    }
  ],
  "queimadas": {
    "focos_100km": 15,
    "fonte": "NASA FIRMS / INPE",
    "atualizado_em": "2026-06-25T09:49:17.998496+00:00"
  },
  "uv": {
    "indice": 7.5,
    "categoria": "Alto",
    "fonte": "Open-Meteo",
    "pico_inicio": "10:00",
    "pico_fim": "14:00"
  },
  "qualidade_ar": {
    "indice": 20,
    "categoria": "Boa",
    "principal_poluente": "PM2.5",
    "pm25": 3.9,
    "pm10": 4.8,
    "no2": 1.6,
    "o3": 52.0,
    "fonte": "Open-Meteo / Copernicus",
    "atualizado_em": "2026-06-23T11:13:45.052106+00:00"
  },
  "sol": {
    "nascer": "05:54",
    "por": "17:49",
    "duracao_h": 11.9,
    "estacao": "Inverno",
    "fonte": "Open-Meteo"
  },
  "lua": {
    "nome": "Quarto Crescente",
    "iluminacao_pct": 99.0,
    "fase_pct": 26.7,
    "dias_proxima_cheia": 7,
    "fonte": "Cálculo astronômico"
  },
  "temperatura_atual": 28.1,
  "vento": {
    "velocidade_kmh": 5.8,
    "direcao_graus": 70,
    "direcao": "ENE",
    "max_kmh": 12.9,
    "rajada_kmh": 25.2,
    "direcao_dominante": "NE",
    "fonte": "Open-Meteo"
  },
  "umidade_pct": 76,
  "pressao_hpa": 1013,
  "ponto_orvalho_c": 23.5,
  "dengue": {
    "nivel_alerta": 1,
    "nivel_label": "Atenção",
    "nivel_incidencia": 0,
    "nivel_incidencia_label": "Baixa",
    "casos_semana": 0,
    "casos_estimados": 0,
    "semana_epidemiologica": 202620,
    "fonte": "InfoDengue / Fiocruz / SVS",
    "atualizado_em": "2026-06-01T22:07:55.191770-03:00"
  },
  "chikungunya": {
    "nivel_alerta": 1,
    "nivel_label": "Atenção",
    "nivel_incidencia": 0,
    "nivel_incidencia_label": "Baixa",
    "casos_semana": 0,
    "casos_estimados": 0,
    "semana_epidemiologica": 202620,
    "fonte": "InfoDengue / Fiocruz / SVS",
    "atualizado_em": "2026-06-01T22:07:55.191770-03:00"
  },
  "_clima_em": "2026-06-23T11:13:45.052106+00:00"
}