{
  "cidade": "Dom Viçoso",
  "estado": "MG",
  "slug": "dom-vicoso",
  "latitude": -22.2286,
  "longitude": -45.1428,
  "atualizado_em": "2026-06-07T08:36:29.686383+00:00",
  "previsao": [
    {
      "data": "2026-06-07",
      "min": 7,
      "max": 20,
      "condicao": "Parcialmente Nublado",
      "condicao_codigo": "pn",
      "chuva_mm": 0,
      "umidade": 0,
      "uv": 0.0
    },
    {
      "data": "2026-06-08",
      "min": 6,
      "max": 23,
      "condicao": "Parcialmente Nublado",
      "condicao_codigo": "pn",
      "chuva_mm": 0,
      "umidade": 0,
      "uv": 0.0
    },
    {
      "data": "2026-06-09",
      "min": 9,
      "max": 21,
      "condicao": "Parcialmente Nublado",
      "condicao_codigo": "pn",
      "chuva_mm": 0,
      "umidade": 0,
      "uv": 0.0
    },
    {
      "data": "2026-06-10",
      "min": 11,
      "max": 22,
      "condicao": "Parcialmente Nublado",
      "condicao_codigo": "pn",
      "chuva_mm": 0,
      "umidade": 0,
      "uv": 0.0
    }
  ],
  "reservatorio": {
    "nome": "Funil",
    "nivel_pct": 38.4,
    "variacao_semana_pct": 0.0,
    "data_medicao": "2026-06-04",
    "distancia_km": 68.0,
    "aproximado": true,
    "nota": "Reservatório hidrelétrico mais próximo (68km). Pode não ser o sistema de abastecimento desta cidade.",
    "fonte": "ONS / ANA",
    "atualizado_em": "2026-06-06T09:06:06.382346+00:00"
  },
  "queimadas": {
    "focos_100km": 4,
    "fonte": "NASA FIRMS / INPE",
    "atualizado_em": "2026-06-06T09:06:08.644870+00:00"
  },
  "uv": {
    "indice": 5.5,
    "categoria": "Moderado",
    "fonte": "Open-Meteo",
    "pico_inicio": "10:00",
    "pico_fim": "14:00"
  },
  "qualidade_ar": {
    "indice": 24,
    "categoria": "Boa",
    "principal_poluente": "PM2.5",
    "pm25": 9.8,
    "pm10": 11.6,
    "no2": 7.8,
    "o3": 37.0,
    "fonte": "Open-Meteo / Copernicus",
    "atualizado_em": "2026-06-06T10:01:22.845096+00:00"
  },
  "sol": {
    "nascer": "06:34",
    "por": "17:23",
    "duracao_h": 10.8,
    "estacao": "Outono",
    "fonte": "Open-Meteo"
  },
  "lua": {
    "nome": "Gibosa Minguante",
    "iluminacao_pct": 93.0,
    "fase_pct": 69.2,
    "dias_proxima_cheia": 6,
    "fonte": "Cálculo astronômico"
  },
  "temperatura_atual": 9.3,
  "vento": {
    "velocidade_kmh": 0.5,
    "direcao_graus": 225,
    "direcao": "SO",
    "max_kmh": 6.5,
    "rajada_kmh": 20.9,
    "direcao_dominante": "NNE",
    "fonte": "Open-Meteo"
  },
  "umidade_pct": 93,
  "pressao_hpa": 1023,
  "ponto_orvalho_c": 8.3,
  "dengue": {
    "nivel_alerta": 1,
    "nivel_label": "Atenção",
    "nivel_incidencia": 0,
    "nivel_incidencia_label": "Baixa",
    "casos_semana": 0,
    "casos_estimados": 0,
    "semana_epidemiologica": 202620,
    "fonte": "InfoDengue / Fiocruz / SVS",
    "atualizado_em": "2026-06-01T22:07:55.191770-03:00"
  },
  "chikungunya": {
    "nivel_alerta": 1,
    "nivel_label": "Atenção",
    "nivel_incidencia": 0,
    "nivel_incidencia_label": "Baixa",
    "casos_semana": 0,
    "casos_estimados": 0,
    "semana_epidemiologica": 202620,
    "fonte": "InfoDengue / Fiocruz / SVS",
    "atualizado_em": "2026-06-01T22:07:55.191770-03:00"
  },
  "_clima_em": "2026-06-06T10:01:22.845096+00:00"
}