{
  "cidade": "Mairinque",
  "estado": "SP",
  "slug": "mairinque",
  "latitude": -23.508,
  "longitude": -47.2293,
  "atualizado_em": "2026-06-13T10:26:02.639374+00:00",
  "previsao": [
    {
      "data": "2026-06-13",
      "min": 15.4,
      "max": 20.4,
      "condicao": "Chuva leve",
      "condicao_codigo": 61,
      "chuva_mm": 3.3,
      "uv": 4.2,
      "nascer_sol": "06:48",
      "por_sol": "17:30"
    },
    {
      "data": "2026-06-14",
      "min": 15.7,
      "max": 19.7,
      "condicao": "Chuvisco leve",
      "condicao_codigo": 51,
      "chuva_mm": 1.6,
      "uv": 2.1,
      "nascer_sol": "06:48",
      "por_sol": "17:30"
    },
    {
      "data": "2026-06-15",
      "min": 14.1,
      "max": 17.6,
      "condicao": "Chuva leve",
      "condicao_codigo": 61,
      "chuva_mm": 5.1,
      "uv": 0.5,
      "nascer_sol": "06:48",
      "por_sol": "17:30"
    },
    {
      "data": "2026-06-16",
      "min": 13.3,
      "max": 19.3,
      "condicao": "Chuvisco leve",
      "condicao_codigo": 51,
      "chuva_mm": 1.0,
      "uv": 4.8,
      "nascer_sol": "06:49",
      "por_sol": "17:30"
    },
    {
      "data": "2026-06-17",
      "min": 11.9,
      "max": 19.8,
      "condicao": "Encoberto",
      "condicao_codigo": 3,
      "chuva_mm": 0,
      "uv": 5.2,
      "nascer_sol": "06:49",
      "por_sol": "17:30"
    },
    {
      "data": "2026-06-18",
      "min": 11.5,
      "max": 19.5,
      "condicao": "Parcialmente nublado",
      "condicao_codigo": 2,
      "chuva_mm": 0,
      "uv": 5.0,
      "nascer_sol": "06:49",
      "por_sol": "17:30"
    },
    {
      "data": "2026-06-19",
      "min": 11.5,
      "max": 21.6,
      "condicao": "Encoberto",
      "condicao_codigo": 3,
      "chuva_mm": 0,
      "uv": 5.0,
      "nascer_sol": "06:49",
      "por_sol": "17:31"
    }
  ],
  "reservatorio": {
    "nome": "Rio Claro",
    "nivel_pct": 64.3,
    "variacao_semana_pct": -0.8,
    "variacao_diaria_pct": -0.115,
    "data_medicao": "2026-06-12",
    "sistema_id": 69,
    "fonte": "SABESP",
    "atualizado_em": "2026-06-12T12:17:30.048181+00:00"
  },
  "queimadas": {
    "focos_100km": 6,
    "fonte": "NASA FIRMS / INPE",
    "atualizado_em": "2026-06-13T09:41:22.926869+00:00"
  },
  "uv": {
    "indice": 4.2,
    "categoria": "Moderado",
    "fonte": "Open-Meteo",
    "pico_inicio": "10:00",
    "pico_fim": "14:00"
  },
  "qualidade_ar": {
    "indice": 18,
    "categoria": "Boa",
    "principal_poluente": "PM2.5",
    "pm25": 2.0,
    "pm10": 2.1,
    "no2": 6.3,
    "o3": 35.0,
    "fonte": "Open-Meteo / Copernicus",
    "atualizado_em": "2026-06-13T10:26:02.639374+00:00"
  },
  "sol": {
    "nascer": "06:48",
    "por": "17:30",
    "duracao_h": 10.7,
    "estacao": "Outono",
    "fonte": "Open-Meteo"
  },
  "lua": {
    "nome": "Minguante",
    "iluminacao_pct": 43.0,
    "fase_pct": 92.9,
    "dias_proxima_cheia": 13,
    "fonte": "Cálculo astronômico"
  },
  "temperatura_atual": 15.9,
  "dengue": {
    "nivel_alerta": 2,
    "nivel_label": "Alerta",
    "nivel_incidencia": 1,
    "nivel_incidencia_label": "Média",
    "casos_semana": 0,
    "casos_estimados": 5,
    "semana_epidemiologica": 202620,
    "fonte": "InfoDengue / Fiocruz / SVS",
    "atualizado_em": "2026-06-01T22:07:55.191770-03:00"
  },
  "chikungunya": {
    "nivel_alerta": 1,
    "nivel_label": "Atenção",
    "nivel_incidencia": 0,
    "nivel_incidencia_label": "Baixa",
    "casos_semana": 0,
    "casos_estimados": 0,
    "semana_epidemiologica": 202620,
    "fonte": "InfoDengue / Fiocruz / SVS",
    "atualizado_em": "2026-06-01T22:07:55.191770-03:00"
  },
  "_clima_em": "2026-06-13T10:26:02.639374+00:00",
  "vento": {
    "velocidade_kmh": 9.4,
    "direcao_graus": 294,
    "direcao": "ONO",
    "max_kmh": 20.9,
    "rajada_kmh": 50.0,
    "direcao_dominante": "NO",
    "fonte": "Open-Meteo"
  },
  "umidade_pct": 99,
  "pressao_hpa": 1017,
  "ponto_orvalho_c": 15.8
}