{
  "cidade": "Mombuca",
  "estado": "SP",
  "slug": "mombuca",
  "latitude": -22.9427,
  "longitude": -47.602,
  "atualizado_em": "2026-06-07T10:26:33.424181+00:00",
  "previsao": [
    {
      "data": "2026-06-07",
      "min": 9.7,
      "max": 21.9,
      "condicao": "Encoberto",
      "condicao_codigo": 3,
      "chuva_mm": 0,
      "uv": 5.3,
      "nascer_sol": "06:46",
      "por_sol": "17:32"
    },
    {
      "data": "2026-06-08",
      "min": 8.8,
      "max": 23.9,
      "condicao": "Encoberto",
      "condicao_codigo": 3,
      "chuva_mm": 0,
      "uv": 5.2,
      "nascer_sol": "06:46",
      "por_sol": "17:32"
    },
    {
      "data": "2026-06-09",
      "min": 10.4,
      "max": 24.8,
      "condicao": "Encoberto",
      "condicao_codigo": 3,
      "chuva_mm": 0,
      "uv": 4.8,
      "nascer_sol": "06:47",
      "por_sol": "17:32"
    },
    {
      "data": "2026-06-10",
      "min": 13.1,
      "max": 20.9,
      "condicao": "Chuva leve",
      "condicao_codigo": 61,
      "chuva_mm": 6.0,
      "uv": 0.6,
      "nascer_sol": "06:47",
      "por_sol": "17:32"
    },
    {
      "data": "2026-06-11",
      "min": 15.5,
      "max": 22.2,
      "condicao": "Chuvisco denso",
      "condicao_codigo": 55,
      "chuva_mm": 9.8,
      "uv": 3.8,
      "nascer_sol": "06:47",
      "por_sol": "17:32"
    },
    {
      "data": "2026-06-12",
      "min": 17.4,
      "max": 23.1,
      "condicao": "Chuvisco moderado",
      "condicao_codigo": 53,
      "chuva_mm": 5.7,
      "uv": 4.3,
      "nascer_sol": "06:48",
      "por_sol": "17:32"
    },
    {
      "data": "2026-06-13",
      "min": 17.7,
      "max": 21.9,
      "condicao": "Chuvisco moderado",
      "condicao_codigo": 53,
      "chuva_mm": 7.2,
      "uv": 3.0,
      "nascer_sol": "06:48",
      "por_sol": "17:32"
    }
  ],
  "queimadas": {
    "focos_100km": 19,
    "fonte": "NASA FIRMS / INPE",
    "atualizado_em": "2026-06-06T09:06:08.644870+00:00"
  },
  "reservatorio": {
    "nome": "B. Bonita",
    "nivel_pct": 86.7,
    "variacao_semana_pct": 0.0,
    "data_medicao": "2026-06-05",
    "distancia_km": 106.6,
    "aproximado": true,
    "nota": "Reservatório hidrelétrico mais próximo (107km). Pode não ser o sistema de abastecimento desta cidade.",
    "fonte": "ONS / ANA",
    "atualizado_em": "2026-06-07T09:43:36.840302+00:00"
  },
  "uv": {
    "indice": 5.3,
    "categoria": "Moderado",
    "fonte": "Open-Meteo",
    "pico_inicio": "10:00",
    "pico_fim": "14:00"
  },
  "qualidade_ar": {
    "indice": 111,
    "categoria": "Ruim para grupos sensíveis",
    "principal_poluente": "PM2.5",
    "pm25": 79.6,
    "pm10": 82.9,
    "no2": 45.5,
    "o3": 25.0,
    "fonte": "Open-Meteo / Copernicus",
    "atualizado_em": "2026-06-07T10:26:33.424181+00:00"
  },
  "sol": {
    "nascer": "06:46",
    "por": "17:32",
    "duracao_h": 10.8,
    "estacao": "Outono",
    "fonte": "Open-Meteo"
  },
  "lua": {
    "nome": "Gibosa Minguante",
    "iluminacao_pct": 99.0,
    "fase_pct": 72.6,
    "dias_proxima_cheia": 7,
    "fonte": "Cálculo astronômico"
  },
  "temperatura_atual": 10.3,
  "dengue": {
    "nivel_alerta": 1,
    "nivel_label": "Atenção",
    "nivel_incidencia": 0,
    "nivel_incidencia_label": "Baixa",
    "casos_semana": 0,
    "casos_estimados": 0,
    "semana_epidemiologica": 202620,
    "fonte": "InfoDengue / Fiocruz / SVS",
    "atualizado_em": "2026-06-01T22:07:55.191770-03:00"
  },
  "chikungunya": {
    "nivel_alerta": 1,
    "nivel_label": "Atenção",
    "nivel_incidencia": 0,
    "nivel_incidencia_label": "Baixa",
    "casos_semana": 0,
    "casos_estimados": 0,
    "semana_epidemiologica": 202620,
    "fonte": "InfoDengue / Fiocruz / SVS",
    "atualizado_em": "2026-06-01T22:07:55.191770-03:00"
  },
  "_clima_em": "2026-06-07T10:26:33.424181+00:00",
  "vento": {
    "velocidade_kmh": 2.8,
    "direcao_graus": 45,
    "direcao": "NE",
    "max_kmh": 5.9,
    "rajada_kmh": 16.9,
    "direcao_dominante": "E",
    "fonte": "Open-Meteo"
  },
  "umidade_pct": 99,
  "pressao_hpa": 1019,
  "ponto_orvalho_c": 10.2
}