{
  "cidade": "Caiçara",
  "estado": "RS",
  "slug": "caicara",
  "latitude": -27.2466,
  "longitude": -53.4666,
  "atualizado_em": "2026-06-03T12:39:59.933921+00:00",
  "previsao": [
    {
      "data": "2026-06-03",
      "min": 10.2,
      "max": 21.7,
      "condicao": "Encoberto",
      "condicao_codigo": 3,
      "chuva_mm": 0,
      "uv": 4.7,
      "nascer_sol": "07:16",
      "por_sol": "17:47"
    },
    {
      "data": "2026-06-04",
      "min": 10.6,
      "max": 20.6,
      "condicao": "Encoberto",
      "condicao_codigo": 3,
      "chuva_mm": 0,
      "uv": 4.7,
      "nascer_sol": "07:17",
      "por_sol": "17:47"
    },
    {
      "data": "2026-06-05",
      "min": 11.5,
      "max": 22.0,
      "condicao": "Encoberto",
      "condicao_codigo": 3,
      "chuva_mm": 0,
      "uv": 4.1,
      "nascer_sol": "07:17",
      "por_sol": "17:47"
    },
    {
      "data": "2026-06-06",
      "min": 10.0,
      "max": 22.1,
      "condicao": "Parcialmente nublado",
      "condicao_codigo": 2,
      "chuva_mm": 0,
      "uv": 4.7,
      "nascer_sol": "07:18",
      "por_sol": "17:47"
    },
    {
      "data": "2026-06-07",
      "min": 9.9,
      "max": 21.2,
      "condicao": "Encoberto",
      "condicao_codigo": 3,
      "chuva_mm": 0,
      "uv": 4.0,
      "nascer_sol": "07:18",
      "por_sol": "17:47"
    },
    {
      "data": "2026-06-08",
      "min": 11.4,
      "max": 17.3,
      "condicao": "Chuvisco denso",
      "condicao_codigo": 55,
      "chuva_mm": 10.0,
      "uv": 1.2,
      "nascer_sol": "07:19",
      "por_sol": "17:46"
    },
    {
      "data": "2026-06-09",
      "min": 9.9,
      "max": 14.5,
      "condicao": "Chuvisco denso",
      "condicao_codigo": 55,
      "chuva_mm": 2.6,
      "uv": 3.5,
      "nascer_sol": "07:19",
      "por_sol": "17:46"
    }
  ],
  "reservatorio": {
    "nome": "Foz Chapeco",
    "nivel_pct": 37.7,
    "variacao_semana_pct": 0.0,
    "data_medicao": "2026-06-03",
    "distancia_km": 43.1,
    "aproximado": true,
    "nota": "Reservatório hidrelétrico mais próximo (43km). Pode não ser o sistema de abastecimento desta cidade.",
    "fonte": "ONS / ANA",
    "atualizado_em": "2026-06-05T10:29:24.962481+00:00"
  },
  "queimadas": {
    "focos_100km": 8,
    "fonte": "NASA FIRMS / INPE",
    "atualizado_em": "2026-06-05T10:29:27.670806+00:00"
  },
  "uv": {
    "indice": 4.7,
    "categoria": "Moderado",
    "fonte": "Open-Meteo",
    "pico_inicio": "10:00",
    "pico_fim": "14:00"
  },
  "qualidade_ar": {
    "indice": 75,
    "categoria": "Moderada",
    "principal_poluente": "PM2.5",
    "pm25": 27.5,
    "pm10": 28.5,
    "no2": 8.8,
    "o3": 35.0,
    "fonte": "Open-Meteo / Copernicus",
    "atualizado_em": "2026-06-03T12:39:59.933921+00:00"
  },
  "sol": {
    "nascer": "07:16",
    "por": "17:47",
    "duracao_h": 10.5,
    "estacao": "Inverno",
    "fonte": "Open-Meteo"
  },
  "lua": {
    "nome": "Cheia",
    "iluminacao_pct": 54.0,
    "fase_pct": 59.0,
    "dias_proxima_cheia": 3,
    "fonte": "Cálculo astronômico"
  },
  "temperatura_atual": 15.0,
  "dengue": {
    "nivel_alerta": 1,
    "nivel_label": "Atenção",
    "nivel_incidencia": 0,
    "nivel_incidencia_label": "Baixa",
    "casos_semana": 0,
    "casos_estimados": 0,
    "semana_epidemiologica": 202620,
    "fonte": "InfoDengue / Fiocruz / SVS",
    "atualizado_em": "2026-06-01T22:07:55.191770-03:00"
  },
  "chikungunya": {
    "nivel_alerta": 1,
    "nivel_label": "Atenção",
    "nivel_incidencia": 0,
    "nivel_incidencia_label": "Baixa",
    "casos_semana": 0,
    "casos_estimados": 0,
    "semana_epidemiologica": 202620,
    "fonte": "InfoDengue / Fiocruz / SVS",
    "atualizado_em": "2026-06-01T22:07:55.191770-03:00"
  },
  "_clima_em": "2026-06-03T12:39:59.933921+00:00",
  "vento": {
    "velocidade_kmh": 7.7,
    "direcao_graus": 72,
    "direcao": "ENE",
    "max_kmh": 8.3,
    "rajada_kmh": 19.4,
    "direcao_dominante": "ESE",
    "fonte": "Open-Meteo"
  },
  "umidade_pct": 76,
  "pressao_hpa": 1026,
  "ponto_orvalho_c": 10.8
}