{
  "cidade": "Morrinhos do Sul",
  "estado": "RS",
  "slug": "morrinhos-do-sul",
  "latitude": -29.3376,
  "longitude": -49.9542,
  "atualizado_em": "2026-06-10T11:37:09.052739+00:00",
  "previsao": [
    {
      "data": "2026-06-10",
      "min": 9.3,
      "max": 16.3,
      "condicao": "Encoberto",
      "condicao_codigo": 3,
      "chuva_mm": 0,
      "uv": 3.0,
      "nascer_sol": "07:10",
      "por_sol": "17:28"
    },
    {
      "data": "2026-06-11",
      "min": 10.9,
      "max": 19.0,
      "condicao": "Chuva moderada",
      "condicao_codigo": 63,
      "chuva_mm": 8.9,
      "uv": 3.5,
      "nascer_sol": "07:10",
      "por_sol": "17:28"
    },
    {
      "data": "2026-06-12",
      "min": 13.6,
      "max": 18.9,
      "condicao": "Chuva isolada leve",
      "condicao_codigo": 80,
      "chuva_mm": 9.5,
      "uv": 2.5,
      "nascer_sol": "07:11",
      "por_sol": "17:28"
    },
    {
      "data": "2026-06-13",
      "min": 10.5,
      "max": 18.4,
      "condicao": "Encoberto",
      "condicao_codigo": 3,
      "chuva_mm": 0,
      "uv": 3.5,
      "nascer_sol": "07:11",
      "por_sol": "17:28"
    },
    {
      "data": "2026-06-14",
      "min": 10.0,
      "max": 15.3,
      "condicao": "Chuvisco leve",
      "condicao_codigo": 51,
      "chuva_mm": 1.5,
      "uv": 3.7,
      "nascer_sol": "07:11",
      "por_sol": "17:28"
    },
    {
      "data": "2026-06-15",
      "min": 9.4,
      "max": 13.8,
      "condicao": "Encoberto",
      "condicao_codigo": 3,
      "chuva_mm": 0,
      "uv": 3.9,
      "nascer_sol": "07:12",
      "por_sol": "17:28"
    },
    {
      "data": "2026-06-16",
      "min": 7.3,
      "max": 15.0,
      "condicao": "Parcialmente nublado",
      "condicao_codigo": 2,
      "chuva_mm": 0,
      "uv": 3.9,
      "nascer_sol": "07:12",
      "por_sol": "17:28"
    }
  ],
  "reservatorio": {
    "nome": "Canastra",
    "nivel_pct": 0.0,
    "variacao_semana_pct": 0.0,
    "data_medicao": "2026-06-09",
    "distancia_km": 77.0,
    "aproximado": true,
    "nota": "Reservatório hidrelétrico mais próximo (77km). Pode não ser o sistema de abastecimento desta cidade.",
    "fonte": "ONS / ANA",
    "atualizado_em": "2026-06-11T11:04:53.205773+00:00"
  },
  "queimadas": {
    "focos_100km": 0,
    "fonte": "NASA FIRMS / INPE",
    "atualizado_em": "2026-06-11T11:04:55.601799+00:00"
  },
  "uv": {
    "indice": 3.0,
    "categoria": "Moderado",
    "fonte": "Open-Meteo",
    "pico_inicio": "10:00",
    "pico_fim": "14:00"
  },
  "qualidade_ar": {
    "indice": 25,
    "categoria": "Boa",
    "principal_poluente": "PM2.5",
    "pm25": 10.0,
    "pm10": 10.0,
    "no2": 4.7,
    "o3": 13.0,
    "fonte": "Open-Meteo / Copernicus",
    "atualizado_em": "2026-06-10T11:37:09.052739+00:00"
  },
  "sol": {
    "nascer": "07:10",
    "por": "17:28",
    "duracao_h": 10.3,
    "estacao": "Outono",
    "fonte": "Open-Meteo"
  },
  "lua": {
    "nome": "Quarto Minguante",
    "iluminacao_pct": 88.0,
    "fase_pct": 82.7,
    "dias_proxima_cheia": 10,
    "fonte": "Cálculo astronômico"
  },
  "temperatura_atual": 13.2,
  "dengue": {
    "nivel_alerta": 1,
    "nivel_label": "Atenção",
    "nivel_incidencia": 0,
    "nivel_incidencia_label": "Baixa",
    "casos_semana": 0,
    "casos_estimados": 0,
    "semana_epidemiologica": 202620,
    "fonte": "InfoDengue / Fiocruz / SVS",
    "atualizado_em": "2026-06-01T22:07:55.191770-03:00"
  },
  "chikungunya": {
    "nivel_alerta": 1,
    "nivel_label": "Atenção",
    "nivel_incidencia": 0,
    "nivel_incidencia_label": "Baixa",
    "casos_semana": 0,
    "casos_estimados": 0,
    "semana_epidemiologica": 202620,
    "fonte": "InfoDengue / Fiocruz / SVS",
    "atualizado_em": "2026-06-01T22:07:55.191770-03:00"
  },
  "_clima_em": "2026-06-10T11:37:09.052739+00:00",
  "vento": {
    "velocidade_kmh": 2.0,
    "direcao_graus": 5,
    "direcao": "N",
    "max_kmh": 5.3,
    "rajada_kmh": 16.2,
    "direcao_dominante": "N",
    "fonte": "Open-Meteo"
  },
  "umidade_pct": 79,
  "pressao_hpa": 1018,
  "ponto_orvalho_c": 9.6
}