{
  "cidade": "Três Cachoeiras",
  "estado": "RS",
  "slug": "tres-cachoeiras",
  "latitude": -29.4744,
  "longitude": -49.9632,
  "atualizado_em": "2026-06-26T10:48:23.909923+00:00",
  "previsao": [
    {
      "data": "2026-06-26",
      "min": 8.8,
      "max": 15.8,
      "condicao": "Céu limpo",
      "condicao_codigo": 0,
      "chuva_mm": 0,
      "uv": 4.2,
      "nascer_sol": "07:14",
      "por_sol": "17:30"
    },
    {
      "data": "2026-06-27",
      "min": 7.8,
      "max": 17.3,
      "condicao": "Encoberto",
      "condicao_codigo": 3,
      "chuva_mm": 0,
      "uv": 4.1,
      "nascer_sol": "07:15",
      "por_sol": "17:30"
    },
    {
      "data": "2026-06-28",
      "min": 12.7,
      "max": 17.7,
      "condicao": "Tempestade",
      "condicao_codigo": 95,
      "chuva_mm": 24.7,
      "uv": 1.1,
      "nascer_sol": "07:15",
      "por_sol": "17:31"
    },
    {
      "data": "2026-06-29",
      "min": 12.5,
      "max": 15.9,
      "condicao": "Chuvisco leve",
      "condicao_codigo": 51,
      "chuva_mm": 0.4,
      "uv": 3.1,
      "nascer_sol": "07:15",
      "por_sol": "17:31"
    },
    {
      "data": "2026-06-30",
      "min": 11.7,
      "max": 14.7,
      "condicao": "Chuva isolada leve",
      "condicao_codigo": 80,
      "chuva_mm": 10.2,
      "uv": 0.5,
      "nascer_sol": "07:15",
      "por_sol": "17:31"
    },
    {
      "data": "2026-07-01",
      "min": 13.3,
      "max": 17.0,
      "condicao": "Chuva isolada leve",
      "condicao_codigo": 80,
      "chuva_mm": 12.0,
      "uv": 0.8,
      "nascer_sol": "07:15",
      "por_sol": "17:32"
    },
    {
      "data": "2026-07-02",
      "min": 13.7,
      "max": 17.5,
      "condicao": "Chuvisco leve",
      "condicao_codigo": 51,
      "chuva_mm": 0.6,
      "uv": 0.3,
      "nascer_sol": "07:15",
      "por_sol": "17:32"
    }
  ],
  "reservatorio": {
    "nome": "Canastra",
    "nivel_pct": 0.0,
    "variacao_semana_pct": 0.0,
    "data_medicao": "2026-06-25",
    "distancia_km": 76.3,
    "aproximado": true,
    "nota": "Reservatório hidrelétrico mais próximo (76km). Pode não ser o sistema de abastecimento desta cidade.",
    "fonte": "ONS / ANA",
    "atualizado_em": "2026-06-27T09:08:53.564381+00:00"
  },
  "queimadas": {
    "focos_100km": 14,
    "fonte": "NASA FIRMS / INPE",
    "atualizado_em": "2026-06-27T09:08:55.876779+00:00"
  },
  "uv": {
    "indice": 4.2,
    "categoria": "Moderado",
    "fonte": "Open-Meteo",
    "pico_inicio": "10:00",
    "pico_fim": "14:00"
  },
  "qualidade_ar": {
    "indice": 19,
    "categoria": "Boa",
    "principal_poluente": "PM2.5",
    "pm25": 1.7,
    "pm10": 1.7,
    "no2": 5.1,
    "o3": 31.0,
    "fonte": "Open-Meteo / Copernicus",
    "atualizado_em": "2026-06-26T10:48:23.909923+00:00"
  },
  "sol": {
    "nascer": "07:14",
    "por": "17:30",
    "duracao_h": 10.3,
    "estacao": "Inverno",
    "fonte": "Open-Meteo"
  },
  "lua": {
    "nome": "Quarto Crescente",
    "iluminacao_pct": 73.0,
    "fase_pct": 36.9,
    "dias_proxima_cheia": 4,
    "fonte": "Cálculo astronômico"
  },
  "temperatura_atual": 9.5,
  "dengue": {
    "nivel_alerta": 1,
    "nivel_label": "Atenção",
    "nivel_incidencia": 0,
    "nivel_incidencia_label": "Baixa",
    "casos_semana": 0,
    "casos_estimados": 0,
    "semana_epidemiologica": 202620,
    "fonte": "InfoDengue / Fiocruz / SVS",
    "atualizado_em": "2026-06-01T22:07:55.191770-03:00"
  },
  "chikungunya": {
    "nivel_alerta": 1,
    "nivel_label": "Atenção",
    "nivel_incidencia": 0,
    "nivel_incidencia_label": "Baixa",
    "casos_semana": 0,
    "casos_estimados": 0,
    "semana_epidemiologica": 202620,
    "fonte": "InfoDengue / Fiocruz / SVS",
    "atualizado_em": "2026-06-01T22:07:55.191770-03:00"
  },
  "_clima_em": "2026-06-26T10:48:23.909923+00:00",
  "vento": {
    "velocidade_kmh": 5.1,
    "direcao_graus": 293,
    "direcao": "ONO",
    "max_kmh": 8.5,
    "rajada_kmh": 19.8,
    "direcao_dominante": "ONO",
    "fonte": "Open-Meteo"
  },
  "umidade_pct": 76,
  "pressao_hpa": 1024,
  "ponto_orvalho_c": 5.5
}