{
  "cidade": "Coxixola",
  "estado": "PB",
  "slug": "coxixola",
  "latitude": -7.6452,
  "longitude": -36.6342,
  "atualizado_em": "2026-06-11T12:07:57.965533+00:00",
  "previsao": [
    {
      "data": "2026-06-11",
      "min": 20.6,
      "max": 29.4,
      "condicao": "Chuvisco leve",
      "condicao_codigo": 51,
      "chuva_mm": 0.4,
      "uv": 7.5,
      "nascer_sol": "05:35",
      "por_sol": "17:16"
    },
    {
      "data": "2026-06-12",
      "min": 19.8,
      "max": 28.3,
      "condicao": "Chuvisco leve",
      "condicao_codigo": 51,
      "chuva_mm": 0.2,
      "uv": 7.5,
      "nascer_sol": "05:35",
      "por_sol": "17:17"
    },
    {
      "data": "2026-06-13",
      "min": 20.7,
      "max": 30.3,
      "condicao": "Chuvisco leve",
      "condicao_codigo": 51,
      "chuva_mm": 0.3,
      "uv": 7.4,
      "nascer_sol": "05:36",
      "por_sol": "17:17"
    },
    {
      "data": "2026-06-14",
      "min": 19.0,
      "max": 31.0,
      "condicao": "Encoberto",
      "condicao_codigo": 3,
      "chuva_mm": 0,
      "uv": 7.4,
      "nascer_sol": "05:36",
      "por_sol": "17:17"
    },
    {
      "data": "2026-06-15",
      "min": 18.0,
      "max": 29.7,
      "condicao": "Chuvisco leve",
      "condicao_codigo": 51,
      "chuva_mm": 0.9,
      "uv": 7.2,
      "nascer_sol": "05:36",
      "por_sol": "17:17"
    },
    {
      "data": "2026-06-16",
      "min": 19.3,
      "max": 29.4,
      "condicao": "Chuvisco leve",
      "condicao_codigo": 51,
      "chuva_mm": 1.2,
      "uv": 7.0,
      "nascer_sol": "05:36",
      "por_sol": "17:17"
    },
    {
      "data": "2026-06-17",
      "min": 20.7,
      "max": 29.8,
      "condicao": "Chuvisco leve",
      "condicao_codigo": 51,
      "chuva_mm": 1.2,
      "uv": 7.2,
      "nascer_sol": "05:37",
      "por_sol": "17:17"
    }
  ],
  "queimadas": {
    "focos_100km": 0,
    "fonte": "NASA FIRMS / INPE",
    "atualizado_em": "2026-06-11T11:04:55.601799+00:00"
  },
  "uv": {
    "indice": 7.5,
    "categoria": "Alto",
    "fonte": "Open-Meteo",
    "pico_inicio": "10:00",
    "pico_fim": "14:00"
  },
  "qualidade_ar": {
    "indice": 14,
    "categoria": "Boa",
    "principal_poluente": "PM2.5",
    "pm25": 1.0,
    "pm10": 1.5,
    "no2": 0.7,
    "o3": 38.0,
    "fonte": "Open-Meteo / Copernicus",
    "atualizado_em": "2026-06-11T12:07:57.965533+00:00"
  },
  "sol": {
    "nascer": "05:35",
    "por": "17:16",
    "duracao_h": 11.7,
    "estacao": "Outono",
    "fonte": "Open-Meteo"
  },
  "lua": {
    "nome": "Quarto Minguante",
    "iluminacao_pct": 77.0,
    "fase_pct": 86.1,
    "dias_proxima_cheia": 11,
    "fonte": "Cálculo astronômico"
  },
  "temperatura_atual": 25.7,
  "vento": {
    "velocidade_kmh": 19.5,
    "direcao_graus": 133,
    "direcao": "SE",
    "max_kmh": 20.8,
    "rajada_kmh": 37.4,
    "direcao_dominante": "SE",
    "fonte": "Open-Meteo"
  },
  "umidade_pct": 68,
  "pressao_hpa": 1017,
  "ponto_orvalho_c": 19.4,
  "dengue": {
    "nivel_alerta": 1,
    "nivel_label": "Atenção",
    "nivel_incidencia": 0,
    "nivel_incidencia_label": "Baixa",
    "casos_semana": 0,
    "casos_estimados": 0,
    "semana_epidemiologica": 202620,
    "fonte": "InfoDengue / Fiocruz / SVS",
    "atualizado_em": "2026-06-01T22:07:55.191770-03:00"
  },
  "chikungunya": {
    "nivel_alerta": 1,
    "nivel_label": "Atenção",
    "nivel_incidencia": 0,
    "nivel_incidencia_label": "Baixa",
    "casos_semana": 0,
    "casos_estimados": 0,
    "semana_epidemiologica": 202620,
    "fonte": "InfoDengue / Fiocruz / SVS",
    "atualizado_em": "2026-06-01T22:07:55.191770-03:00"
  },
  "_clima_em": "2026-06-11T12:07:57.965533+00:00"
}