{
  "cidade": "Coribe",
  "estado": "BA",
  "slug": "coribe",
  "latitude": -13.8143,
  "longitude": -44.3763,
  "atualizado_em": "2026-06-20T10:30:41.373674+00:00",
  "previsao": [
    {
      "data": "2026-06-20",
      "min": 15.9,
      "max": 27.1,
      "condicao": "Parcialmente nublado",
      "condicao_codigo": 2,
      "chuva_mm": 0,
      "uv": 6.4,
      "nascer_sol": "06:19",
      "por_sol": "17:38"
    },
    {
      "data": "2026-06-21",
      "min": 15.5,
      "max": 28.8,
      "condicao": "Céu limpo",
      "condicao_codigo": 0,
      "chuva_mm": 0,
      "uv": 6.4,
      "nascer_sol": "06:19",
      "por_sol": "17:38"
    },
    {
      "data": "2026-06-22",
      "min": 17.5,
      "max": 28.6,
      "condicao": "Principalmente limpo",
      "condicao_codigo": 1,
      "chuva_mm": 0,
      "uv": 6.4,
      "nascer_sol": "06:20",
      "por_sol": "17:38"
    },
    {
      "data": "2026-06-23",
      "min": 16.9,
      "max": 29.4,
      "condicao": "Céu limpo",
      "condicao_codigo": 0,
      "chuva_mm": 0,
      "uv": 6.4,
      "nascer_sol": "06:20",
      "por_sol": "17:38"
    },
    {
      "data": "2026-06-24",
      "min": 17.3,
      "max": 30.3,
      "condicao": "Encoberto",
      "condicao_codigo": 3,
      "chuva_mm": 0,
      "uv": 6.4,
      "nascer_sol": "06:20",
      "por_sol": "17:39"
    },
    {
      "data": "2026-06-25",
      "min": 19.1,
      "max": 29.4,
      "condicao": "Encoberto",
      "condicao_codigo": 3,
      "chuva_mm": 0,
      "uv": 6.3,
      "nascer_sol": "06:20",
      "por_sol": "17:39"
    },
    {
      "data": "2026-06-26",
      "min": 19.5,
      "max": 26.6,
      "condicao": "Encoberto",
      "condicao_codigo": 3,
      "chuva_mm": 0,
      "uv": 6.2,
      "nascer_sol": "06:20",
      "por_sol": "17:39"
    }
  ],
  "queimadas": {
    "focos_100km": 6,
    "fonte": "NASA FIRMS / INPE",
    "atualizado_em": "2026-06-20T09:47:27.412526+00:00"
  },
  "uv": {
    "indice": 6.4,
    "categoria": "Alto",
    "fonte": "Open-Meteo",
    "pico_inicio": "10:00",
    "pico_fim": "14:00"
  },
  "qualidade_ar": {
    "indice": 17,
    "categoria": "Boa",
    "principal_poluente": "PM2.5",
    "pm25": 4.5,
    "pm10": 6.0,
    "no2": 2.3,
    "o3": 40.0,
    "fonte": "Open-Meteo / Copernicus",
    "atualizado_em": "2026-06-20T10:30:41.373674+00:00"
  },
  "sol": {
    "nascer": "06:19",
    "por": "17:38",
    "duracao_h": 11.3,
    "estacao": "Outono",
    "fonte": "Open-Meteo"
  },
  "lua": {
    "nome": "Crescente",
    "iluminacao_pct": 86.0,
    "fase_pct": 16.6,
    "dias_proxima_cheia": 10,
    "fonte": "Cálculo astronômico"
  },
  "temperatura_atual": 17.6,
  "vento": {
    "velocidade_kmh": 13.5,
    "direcao_graus": 124,
    "direcao": "SE",
    "max_kmh": 13.6,
    "rajada_kmh": 31.0,
    "direcao_dominante": "SE",
    "fonte": "Open-Meteo"
  },
  "umidade_pct": 71,
  "pressao_hpa": 1019,
  "ponto_orvalho_c": 12.3,
  "dengue": {
    "nivel_alerta": 1,
    "nivel_label": "Atenção",
    "nivel_incidencia": 2,
    "nivel_incidencia_label": "Alta",
    "casos_semana": 0,
    "casos_estimados": 19,
    "semana_epidemiologica": 202623,
    "fonte": "InfoDengue / Fiocruz / SVS",
    "atualizado_em": "2026-06-19T12:34:51.582605+00:00"
  },
  "chikungunya": {
    "nivel_alerta": 1,
    "nivel_label": "Atenção",
    "nivel_incidencia": 0,
    "nivel_incidencia_label": "Baixa",
    "casos_semana": 0,
    "casos_estimados": 0,
    "semana_epidemiologica": 202623,
    "fonte": "InfoDengue / Fiocruz / SVS",
    "atualizado_em": "2026-06-19T12:34:51.582605+00:00"
  },
  "_clima_em": "2026-06-20T10:30:41.373674+00:00"
}