{
  "cidade": "Palmeiras",
  "estado": "BA",
  "slug": "palmeiras",
  "latitude": -12.5524,
  "longitude": -41.5539,
  "atualizado_em": "2026-06-07T10:26:33.424181+00:00",
  "previsao": [
    {
      "data": "2026-06-07",
      "min": 15.6,
      "max": 21.6,
      "condicao": "Chuvisco leve",
      "condicao_codigo": 51,
      "chuva_mm": 0.5,
      "uv": 6.8,
      "nascer_sol": "06:03",
      "por_sol": "17:27"
    },
    {
      "data": "2026-06-08",
      "min": 16.1,
      "max": 23.1,
      "condicao": "Chuvisco leve",
      "condicao_codigo": 51,
      "chuva_mm": 0.5,
      "uv": 6.8,
      "nascer_sol": "06:03",
      "por_sol": "17:27"
    },
    {
      "data": "2026-06-09",
      "min": 16.6,
      "max": 23.3,
      "condicao": "Chuvisco leve",
      "condicao_codigo": 51,
      "chuva_mm": 1.5,
      "uv": 6.7,
      "nascer_sol": "06:03",
      "por_sol": "17:27"
    },
    {
      "data": "2026-06-10",
      "min": 16.5,
      "max": 23.8,
      "condicao": "Chuvisco leve",
      "condicao_codigo": 51,
      "chuva_mm": 0.4,
      "uv": 6.8,
      "nascer_sol": "06:03",
      "por_sol": "17:27"
    },
    {
      "data": "2026-06-11",
      "min": 14.4,
      "max": 24.8,
      "condicao": "Céu limpo",
      "condicao_codigo": 0,
      "chuva_mm": 0,
      "uv": 6.4,
      "nascer_sol": "06:04",
      "por_sol": "17:27"
    },
    {
      "data": "2026-06-12",
      "min": 14.6,
      "max": 23.9,
      "condicao": "Encoberto",
      "condicao_codigo": 3,
      "chuva_mm": 0,
      "uv": 6.2,
      "nascer_sol": "06:04",
      "por_sol": "17:28"
    },
    {
      "data": "2026-06-13",
      "min": 17.5,
      "max": 23.8,
      "condicao": "Encoberto",
      "condicao_codigo": 3,
      "chuva_mm": 0,
      "uv": 5.5,
      "nascer_sol": "06:04",
      "por_sol": "17:28"
    }
  ],
  "queimadas": {
    "focos_100km": 0,
    "fonte": "NASA FIRMS / INPE",
    "atualizado_em": "2026-06-06T09:06:08.644870+00:00"
  },
  "uv": {
    "indice": 6.8,
    "categoria": "Alto",
    "fonte": "Open-Meteo",
    "pico_inicio": "10:00",
    "pico_fim": "14:00"
  },
  "qualidade_ar": {
    "indice": 16,
    "categoria": "Boa",
    "principal_poluente": "PM2.5",
    "pm25": 3.1,
    "pm10": 4.1,
    "no2": 6.4,
    "o3": 29.0,
    "fonte": "Open-Meteo / Copernicus",
    "atualizado_em": "2026-06-07T10:26:33.424181+00:00"
  },
  "sol": {
    "nascer": "06:03",
    "por": "17:27",
    "duracao_h": 11.4,
    "estacao": "Outono",
    "fonte": "Open-Meteo"
  },
  "lua": {
    "nome": "Gibosa Minguante",
    "iluminacao_pct": 99.0,
    "fase_pct": 72.6,
    "dias_proxima_cheia": 7,
    "fonte": "Cálculo astronômico"
  },
  "temperatura_atual": 16.4,
  "vento": {
    "velocidade_kmh": 5.7,
    "direcao_graus": 77,
    "direcao": "ENE",
    "max_kmh": 11.3,
    "rajada_kmh": 27.7,
    "direcao_dominante": "E",
    "fonte": "Open-Meteo"
  },
  "umidade_pct": 97,
  "pressao_hpa": 1020,
  "ponto_orvalho_c": 15.9,
  "dengue": {
    "nivel_alerta": 1,
    "nivel_label": "Atenção",
    "nivel_incidencia": 0,
    "nivel_incidencia_label": "Baixa",
    "casos_semana": 0,
    "casos_estimados": 0,
    "semana_epidemiologica": 202620,
    "fonte": "InfoDengue / Fiocruz / SVS",
    "atualizado_em": "2026-06-01T22:07:55.191770-03:00"
  },
  "chikungunya": {
    "nivel_alerta": 1,
    "nivel_label": "Atenção",
    "nivel_incidencia": 0,
    "nivel_incidencia_label": "Baixa",
    "casos_semana": 0,
    "casos_estimados": 0,
    "semana_epidemiologica": 202620,
    "fonte": "InfoDengue / Fiocruz / SVS",
    "atualizado_em": "2026-06-01T22:07:55.191770-03:00"
  },
  "_clima_em": "2026-06-07T10:26:33.424181+00:00"
}